ealocr/__init__.py
ealocr/cli.py
ealocr/config.py
ealocr/craft.py
ealocr/craft_utils.py
ealocr/detection.py
ealocr/easyocr.py
ealocr/export.py
ealocr/imgproc.py
ealocr/recognition.py
ealocr/utils.py
ealocr-1.4.7.dist-info/LICENSE
ealocr-1.4.7.dist-info/METADATA
ealocr-1.4.7.dist-info/WHEEL
ealocr-1.4.7.dist-info/entry_points.txt
ealocr-1.4.7.dist-info/top_level.txt
ealocr-1.4.7.dist-info/RECORD
