Metadata-Version: 2.1
Name: ealocr
Version: 1.4.7
Summary: EasyAimLock forked edition / End-to-End Multi-Lingual Optical Character Recognition (OCR) Solution
Home-page: https://github.com/easyaimlock/easyocr
Download-URL: https://github.com/easyaimlock/easyocr.git
Author: Rakpong Kittinaradorn
Author-email: r.kittinaradorn@gmail.com
License: Apache License 2.0
Keywords: ocr optical character recognition deep learning neural network eal easyaimlock
Platform: UNKNOWN
Classifier: Development Status :: 5 - Production/Stable
License-File: LICENSE
Requires-Dist: torch
Requires-Dist: torchvision (>=0.5)
Requires-Dist: opencv-python-headless (==4.5.3.56)
Requires-Dist: scipy
Requires-Dist: numpy
Requires-Dist: Pillow
Requires-Dist: scikit-image
Requires-Dist: python-bidi
Requires-Dist: PyYAML
